just_logger/__init__.py
just_logger/enums.py
just_logger/exceptions.py
just_logger/logging.py
just_logger/settings.py
just_logger/utils.py
python_just_logger-1.1.1.dist-info/METADATA
python_just_logger-1.1.1.dist-info/WHEEL
python_just_logger-1.1.1.dist-info/top_level.txt
python_just_logger-1.1.1.dist-info/RECORD
