Metadata-Version: 2.1
Name: python-just-logger
Version: 1.1.1
Home-page: https://github.com/duvrdx/just_logger
Author: Eduardo
Author-email: duvrdx@gmail.com
Classifier: Intended Audience :: Developers
Classifier: Operating System :: OS Independent
Classifier: Programming Language :: Python
Classifier: Programming Language :: Python :: 3 :: Only
Classifier: Programming Language :: Python :: 3.10
Requires-Python: >=3.10
Requires-Dist: python-dotenv >=1.0.1
